{ "huangke": [{ "title": "ECMAScript 6入门", "url": "http://es6.ruanyifeng.com/", "desc": "开源的JavaScript语言教程，全面介绍ECMAScript 6新引入的语法特性。", "author": "阮一峰", "tags": ["javascript", "ES6", "NodeJS"] }, { "title": "Git教程", "url": "http://www.liaoxuefeng.com/wiki/0013739516305929606dd18361248578c67b8067c8c017b000", "desc": "史上最浅显易懂的Git教程！", "author": "廖雪峰" }, { "title": "Pro Git book", "url": "https://git-scm.com/book/zh/v2", "desc": "了解git内部原理和使用比较有帮助。", "author": "Scott Chacon & Ben Straub", "tags": ["git"] }, { "title": "vuejs教程", "url": "http://vuejs.org.cn/guide/", "desc": "vuejs的官方中文文档。", "author": "vuejs", "tags": ["javascript", "MVVM", "NodeJS"] }, { "title": "bootstrap", "url": "http://www.runoob.com/bootstrap/bootstrap-tutorial.html", "desc": "Bootstrap，来自 Twitter，是目前最受欢迎的前端框架。", "author": "Twitter", "tags": ["javascript", "css", "Html5"] }, { "title": "Node入门", "url": "http://www.nodebeginner.org/index-zh-cn.html", "desc": "Node入门教材，用node做web开发，流程分析过程比较值得学习。", "author": "Manuel Kiessling", "tags": ["javascript", "NodeJS"] }, { "title": "emmet 网页开发者必备工具", "url": "http://yanxyz.github.io/emmet-docs/", "desc": "Emmet (即之前著名的 Zen Coding) 是一个网页开发者工具，可以大大地提高你的 HTML & CSS 开发效率。", "author": "github", "tags": ["javascript", "html", "css"] }, { "title": "html和css编码规范", "url": "http://codeguide.bootcss.com", "desc": "编写灵活、稳定、高质量的 HTML 和 CSS 代码的规范。", "author": "mdo", "tags": ["html", "css6"] }, { "title": "cordova-tutorial", "url": "http://ccoenraets.github.io/cordova-tutorial/index.html", "desc": "英文版，学习apache cordova的参考资料。", "author": "ccoenraets", "tags": ["cordova"] }, { "title": "diveintohtml5", "url": "http://diveintohtml5.info/", "desc": "英文版本，html5的特性介绍。", "author": "Mark Pilgrim", "tags": ["javascript", "html5"] }, { "title": "vue-router文档", "url": "http://router.vuejs.org/zh-cn/index.html", "desc": "vue-router文档介绍。", "author": "vue router", "tags": ["vuejs", "router"] }, { "title": "Akka doc for JDK1.7", "url": "http://doc.akka.io/docs/akka/2.3.15/java.html", "desc": "Akka是构建高并发、分布式和容错应用的工具包和运行时。", "author": "Akka", "tags": ["Java", "Scala", "Akka"] }, { "title": "Beetl模版手册", "url": "http://ibeetl.com/guide/beetl.html", "desc": "另外一个类似freemaker的java模版引擎beetl官方说明文档。", "author": "李家智", "tags": ["Java", "模版"] }] }
